CHANGES.rst
LICENSE
MANIFEST.in
Makefile
README.rst
setup.cfg
setup.py
PySpace.egg-info/PKG-INFO
PySpace.egg-info/SOURCES.txt
PySpace.egg-info/dependency_links.txt
PySpace.egg-info/not-zip-safe
PySpace.egg-info/requires.txt
PySpace.egg-info/top_level.txt
benchmark/run_benchmarks.py
benchmark/benchmark/__init__.py
benchmark/benchmark/bench_planet.py
benchmark/benchmark/bench_simulator.py
benchmark/benchmark/benchmark.py
docs/Makefile
docs/source/conf.py
docs/source/index.rst
docs/source/installation.rst
docs/source/overview.rst
docs/source/design/framework.rst
docs/source/reference/index.rst
docs/source/reference/planet.rst
docs/source/reference/simulator.rst
docs/source/reference/utils.rst
docs/source/tutorial/tutorial.rst
examples/barnes_galaxy.py
examples/barnes_square_grid.py
examples/barnes_two_planets.py
examples/brute_force_bench.py
examples/brute_force_random.py
examples/brute_force_square_grid.py
examples/brute_force_two_planets.py
pyspace/__init__.py
pyspace/planet.pxd
pyspace/planet.pyx
pyspace/simulator.pxd
pyspace/simulator.pyx
pyspace/utils.py
src/kernels.cu
src/pyspace.cpp
src/pyspace.h