Metadata-Version: 1.0
Name: PySpace
Version: 0.1.0
Summary: A toolbox for galactic simulations.
Home-page: https://github.com/adityapb/pyspace
Author: PySpace developers
Author-email: adityapb1546@gmail.com
License: UNKNOWN
Platform: UNKNOWN
